{
  "headers": [
    {
      "tool_name": "scancode-toolkit",
      "tool_version": "3.2.1rc2",
      "options": {
        "input": [
          "/home/soimkim/git/ort/result/scan/downloads/PyPI/unknown/importlib-resources/3.3.0"
        ],
        "--copyright": true,
        "--ignore": [
          "*.ort.yml",
          "HERE_NOTICE",
          "META-INF/DEPENDENCIES"
        ],
        "--info": true,
        "--json-pp": "/home/soimkim/git/ort/result/scan/native-scan-results/PyPI/unknown/importlib-resources/3.3.0/scan-results_ScanCode.json",
        "--license": true,
        "--processes": "7",
        "--strip-root": true,
        "--timeout": "300.0"
      },
      "notice": "Generated with ScanCode and provided on an \"AS IS\" BASIS, WITHOUT WARRANTIES\nOR CONDITIONS OF ANY KIND, either express or implied. No content created from\nScanCode should be considered or used as legal advice. Consult an Attorney\nfor any legal advice.\nScanCode is a free software code scanning tool from nexB Inc. and others.\nVisit https://github.com/nexB/scancode-toolkit/ for support and download.",
      "start_timestamp": "2020-11-24T113908.421687",
      "end_timestamp": "2020-11-24T113912.709780",
      "duration": 4.28810715675354,
      "message": null,
      "errors": [],
      "extra_data": {
        "files_count": 56
      }
    }
  ],
  "files": [
    {
      "path": ".readthedocs.yml",
      "type": "file",
      "name": ".readthedocs.yml",
      "base_name": ".readthedocs",
      "extension": ".yml",
      "size": 74,
      "date": "2020-11-24",
      "sha1": "eb4dbf3fa8ffcdf61e6511ce29495fce8682d6ac",
      "md5": "050825062deaac6f3935900f2dd9cdf3",
      "sha256": "da684f55ceaa374e1e1121cf746c7415f6c1bf591bf0cccc866b3fe85ff1e845",
      "mime_type": "text/plain",
      "file_type": "ASCII text",
      "programming_language": "ActionScript 3",
      "is_binary": false,
      "is_text": true,
      "is_archive": false,
      "is_media": false,
      "is_source": true,
      "is_script": false,
      "licenses": [],
      "license_expressions": [],
      "percentage_of_license_text": 0,
      "copyrights": [],
      "holders": [],
      "authors": [],
      "files_count": 0,
      "dirs_count": 0,
      "size_count": 0,
      "scan_errors": []
    },
    {
      "path": "codecov.yml",
      "type": "file",
      "name": "codecov.yml",
      "base_name": "codecov",
      "extension": ".yml",
      "size": 55,
      "date": "2020-11-24",
      "sha1": "c324b4d7b35c3a5ac17a672f6e74c16adcafc5ae",
      "md5": "ced5cef031a0a5df03f831e0adf8526b",
      "sha256": "fc566174cff6e41b18fd74b0ab646c705a2c91e194c46b5ed1735426f7756666",
      "mime_type": "text/plain",
      "file_type": "ASCII text",
      "programming_language": "ActionScript 3",
      "is_binary": false,
      "is_text": true,
      "is_archive": false,
      "is_media": false,
      "is_source": true,
      "is_script": false,
      "licenses": [],
      "license_expressions": [],
      "percentage_of_license_text": 0,
      "copyrights": [],
      "holders": [],
      "authors": [],
      "files_count": 0,
      "dirs_count": 0,
      "size_count": 0,
      "scan_errors": []
    },
    {
      "path": "coverage.ini",
      "type": "file",
      "name": "coverage.ini",
      "base_name": "coverage",
      "extension": ".ini",
      "size": 518,
      "date": "2020-11-24",
      "sha1": "afb92cd59f89987eb017c8f453ea93fdb19d935f",
      "md5": "336dc22cf33284b2f3241156f444d78c",
      "sha256": "fd4aa87ac39e46bc85c3f424cb1526333b9ab7f0e70b1ac60a860f597c0aff0a",
      "mime_type": "text/plain",
      "file_type": "ASCII text",
      "programming_language": null,
      "is_binary": false,
      "is_text": true,
      "is_archive": false,
      "is_media": false,
      "is_source": false,
      "is_script": false,
      "licenses": [],
      "license_expressions": [],
      "percentage_of_license_text": 0,
      "copyrights": [],
      "holders": [],
      "authors": [],
      "files_count": 0,
      "dirs_count": 0,
      "size_count": 0,
      "scan_errors": []
    },
    {
      "path": "coverplug.py",
      "type": "file",
      "name": "coverplug.py",
      "base_name": "coverplug",
      "extension": ".py",
      "size": 607,
      "date": "2020-11-24",
      "sha1": "448ec79755faf320ca3cd37e235bcdd18f9dbe79",
      "md5": "e31d16b4159b019ca24289b1fcb770cb",
      "sha256": "81c616e58bfa29cf08758d939c73c0b38c056399d7aff297e9487af1e7a2ab2b",
      "mime_type": "text/plain",
      "file_type": "Python script, ASCII text executable",
      "programming_language": "Python",
      "is_binary": false,
      "is_text": true,
      "is_archive": false,
      "is_media": false,
      "is_source": true,
      "is_script": true,
      "licenses": [],
      "license_expressions": [],
      "percentage_of_license_text": 0,
      "copyrights": [],
      "holders": [],
      "authors": [],
      "files_count": 0,
      "dirs_count": 0,
      "size_count": 0,
      "scan_errors": []
    },
    {
      "path": "DEVELOPER.rst",
      "type": "file",
      "name": "DEVELOPER.rst",
      "base_name": "DEVELOPER",
      "extension": ".rst",
      "size": 232,
      "date": "2020-11-24",
      "sha1": "e62610e16126c92ef08689dfb9686ac2eb120bc6",
      "md5": "56a09eea8f69ccc6881279b1a25522b5",
      "sha256": "9c4780885a8a1189580c1a6a9b7b526f4813f2f5270464ea3552e8ad9f258c95",
      "mime_type": "text/plain",
      "file_type": "ASCII text",
      "programming_language": null,
      "is_binary": false,
      "is_text": true,
      "is_archive": false,
      "is_media": false,
      "is_source": false,
      "is_script": false,
      "licenses": [],
      "license_expressions": [],
      "percentage_of_license_text": 0,
      "copyrights": [],
      "holders": [],
      "authors": [],
      "files_count": 0,
      "dirs_count": 0,
      "size_count": 0,
      "scan_errors": []
    },
    {
      "path": "hook-importlib_resources.py",
      "type": "file",
      "name": "hook-importlib_resources.py",
      "base_name": "hook-importlib_resources",
      "extension": ".py",
      "size": 144,
      "date": "2020-11-24",
      "sha1": "24d4e1f1f3628100186b8a1b0c4e3294b4dd05ca",
      "md5": "e0b33723a5e516b544ae747057fa2b99",
      "sha256": "96e0ddbbc5acbb33f567fccf10e0d916d027a3229c3ceef8e95f733ed2209cf9",
      "mime_type": "text/plain",
      "file_type": "ASCII text",
      "programming_language": "Python",
      "is_binary": false,
      "is_text": true,
      "is_archive": false,
      "is_media": false,
      "is_source": true,
      "is_script": false,
      "licenses": [],
      "license_expressions": [],
      "percentage_of_license_text": 0,
      "copyrights": [],
      "holders": [],
      "authors": [],
      "files_count": 0,
      "dirs_count": 0,
      "size_count": 0,
      "scan_errors": []
    },
    {
      "path": "LICENSE",
      "type": "file",
      "name": "LICENSE",
      "base_name": "LICENSE",
      "extension": "",
      "size": 568,
      "date": "2020-11-24",
      "sha1": "3cd2faf9a752b7838f4b6a634116c24cc3053415",
      "md5": "e81780ac4c0888aaef94a7cb49b55edc",
      "sha256": "b9646315d6066ad6895f6ce25e4d38f08b548254268e78371960402da580dfa5",
      "mime_type": "text/plain",
      "file_type": "ASCII text",
      "programming_language": null,
      "is_binary": false,
      "is_text": true,
      "is_archive": false,
      "is_media": false,
      "is_source": false,
      "is_script": false,
      "licenses": [
        {
          "key": "apache-2.0",
          "score": 100.0,
          "name": "Apache License 2.0",
          "short_name": "Apache 2.0",
          "category": "Permissive",
          "is_exception": false,
          "owner": "Apache Software Foundation",
          "homepage_url": "http://www.apache.org/licenses/",
          "text_url": "http://www.apache.org/licenses/LICENSE-2.0",
          "reference_url": "https://enterprise.dejacode.com/urn/urn:dje:license:apache-2.0",
          "spdx_license_key": "Apache-2.0",
          "spdx_url": "https://spdx.org/licenses/Apache-2.0",
          "start_line": 3,
          "end_line": 13,
          "matched_rule": {
            "identifier": "apache-2.0_7.RULE",
            "license_expression": "apache-2.0",
            "licenses": [
              "apache-2.0"
            ],
            "is_license_text": false,
            "is_license_notice": true,
            "is_license_reference": false,
            "is_license_tag": false,
            "matcher": "2-aho",
            "rule_length": 85,
            "matched_length": 85,
            "match_coverage": 100.0,
            "rule_relevance": 100
          }
        }
      ],
      "license_expressions": [
        "apache-2.0"
      ],
      "percentage_of_license_text": 92.39,
      "copyrights": [
        {
          "value": "Copyright 2017-2019 Brett Cannon, Barry Warsaw",
          "start_line": 1,
          "end_line": 1
        }
      ],
      "holders": [
        {
          "value": "Brett Cannon, Barry Warsaw",
          "start_line": 1,
          "end_line": 1
        }
      ],
      "authors": [],
      "files_count": 0,
      "dirs_count": 0,
      "size_count": 0,
      "scan_errors": []
    },
    {
      "path": "pyproject.toml",
      "type": "file",
      "name": "pyproject.toml",
      "base_name": "pyproject",
      "extension": ".toml",
      "size": 110,
      "date": "2020-11-24",
      "sha1": "0112866e0e28cb05fd483676cb82aecde3b734b9",
      "md5": "c68c4dd5268c7a4d4b77edb7d1bf8864",
      "sha256": "afc058861bc2c592cdbf3b2328578bdc7dc31c165af9f5edf345b84fd6e4c515",
      "mime_type": "text/plain",
      "file_type": "ASCII text",
      "programming_language": null,
      "is_binary": false,
      "is_text": true,
      "is_archive": false,
      "is_media": false,
      "is_source": false,
      "is_script": false,
      "licenses": [],
      "license_expressions": [],
      "percentage_of_license_text": 0,
      "copyrights": [],
      "holders": [],
      "authors": [],
      "files_count": 0,
      "dirs_count": 0,
      "size_count": 0,
      "scan_errors": []
    },
    {
      "path": "README.rst",
      "type": "file",
      "name": "README.rst",
      "base_name": "README",
      "extension": ".rst",
      "size": 670,
      "date": "2020-11-24",
      "sha1": "2c9d07cda0743b539dbbf974ac873eaafa3254c9",
      "md5": "d59b652b68f8a11b3c0984ebba695e48",
      "sha256": "294f4a5d304e895d7c9113697919ad023419829b1c3d62e4503b92559dbcf777",
      "mime_type": "text/plain",
      "file_type": "Dyalog APL transfer",
      "programming_language": null,
      "is_binary": false,
      "is_text": true,
      "is_archive": false,
      "is_media": false,
      "is_source": false,
      "is_script": false,
      "licenses": [],
      "license_expressions": [],
      "percentage_of_license_text": 0,
      "copyrights": [],
      "holders": [],
      "authors": [],
      "files_count": 0,
      "dirs_count": 0,
      "size_count": 0,
      "scan_errors": []
    },
    {
      "path": "setup.cfg",
      "type": "file",
      "name": "setup.cfg",
      "base_name": "setup",
      "extension": ".cfg",
      "size": 1506,
      "date": "2020-11-24",
      "sha1": "02a986d4ae3ae7ba7180ad1751c8f068e1ebf1fe",
      "md5": "2684e4be903e2b59c147276bb4983ab9",
      "sha256": "5d9dec5cdd7e9bf411862a7fd0f8d861498d66ce4d5ecf2ba5fe495993c88cdb",
      "mime_type": "text/plain",
      "file_type": "ASCII text",
      "programming_language": null,
      "is_binary": false,
      "is_text": true,
      "is_archive": false,
      "is_media": false,
      "is_source": false,
      "is_script": false,
      "licenses": [
        {
          "key": "apache-2.0",
          "score": 99.0,
          "name": "Apache License 2.0",
          "short_name": "Apache 2.0",
          "category": "Permissive",
          "is_exception": false,
          "owner": "Apache Software Foundation",
          "homepage_url": "http://www.apache.org/licenses/",
          "text_url": "http://www.apache.org/licenses/LICENSE-2.0",
          "reference_url": "https://enterprise.dejacode.com/urn/urn:dje:license:apache-2.0",
          "spdx_license_key": "Apache-2.0",
          "spdx_url": "https://spdx.org/licenses/Apache-2.0",
          "start_line": 12,
          "end_line": 12,
          "matched_rule": {
            "identifier": "pypi_apache_software_license.RULE",
            "license_expression": "apache-2.0",
            "licenses": [
              "apache-2.0"
            ],
            "is_license_text": false,
            "is_license_notice": false,
            "is_license_reference": false,
            "is_license_tag": true,
            "matcher": "2-aho",
            "rule_length": 6,
            "matched_length": 6,
            "match_coverage": 100.0,
            "rule_relevance": 99.0
          }
        }
      ],
      "license_expressions": [
        "apache-2.0"
      ],
      "percentage_of_license_text": 2.91,
      "copyrights": [],
      "holders": [],
      "authors": [
        {
          "value": "Barry Warsaw",
          "start_line": 4,
          "end_line": 7
        }
      ],
      "files_count": 0,
      "dirs_count": 0,
      "size_count": 0,
      "scan_errors": []
    },
    {
      "path": "setup.py",
      "type": "file",
      "name": "setup.py",
      "base_name": "setup",
      "extension": ".py",
      "size": 58,
      "date": "2020-11-24",
      "sha1": "bbc83f52cb414e7bb2198936f0620b4664c8ac77",
      "md5": "ae0d920f857822acce81f17c642da0e0",
      "sha256": "4a27ece96bfe68ceb86a703434f2ab780578fb625fe12176fd167180d40e9645",
      "mime_type": "text/x-python",
      "file_type": "Python script, ASCII text executable",
      "programming_language": "Python",
      "is_binary": false,
      "is_text": true,
      "is_archive": false,
      "is_media": false,
      "is_source": true,
      "is_script": true,
      "licenses": [],
      "license_expressions": [],
      "percentage_of_license_text": 0,
      "copyrights": [],
      "holders": [],
      "authors": [],
      "files_count": 0,
      "dirs_count": 0,
      "size_count": 0,
      "scan_errors": []
    },
    {
      "path": "tox.ini",
      "type": "file",
      "name": "tox.ini",
      "base_name": "tox",
      "extension": ".ini",
      "size": 1953,
      "date": "2020-11-24",
      "sha1": "5bd6fac584c88fef24b6d105c05560e1c2c78a4b",
      "md5": "4b1e708824820dc046d7be3d7156a1cb",
      "sha256": "2bc5e9dce25cd6b96dae883c7283e2037a7acb5012cebd8356e6f6f05c1f4c7c",
      "mime_type": "text/plain",
      "file_type": "ASCII text",
      "programming_language": null,
      "is_binary": false,
      "is_text": true,
      "is_archive": false,
      "is_media": false,
      "is_source": false,
      "is_script": false,
      "licenses": [],
      "license_expressions": [],
      "percentage_of_license_text": 0,
      "copyrights": [],
      "holders": [],
      "authors": [],
      "files_count": 0,
      "dirs_count": 0,
      "size_count": 0,
      "scan_errors": []
    },
    {
      "path": "update-zips.py",
      "type": "file",
      "name": "update-zips.py",
      "base_name": "update-zips",
      "extension": ".py",
      "size": 1151,
      "date": "2020-11-24",
      "sha1": "bf8f35637b118141bf0e1e34d44141233e4cc91c",
      "md5": "006ed9503892926f19f0fd7401b7f3e2",
      "sha256": "39a31647b9f01669173a55af69c74a78c27586eac6ec3e78724d8a1a16eee9df",
      "mime_type": "text/x-python",
      "file_type": "Python script, ASCII text executable",
      "programming_language": "Python",
      "is_binary": false,
      "is_text": true,
      "is_archive": false,
      "is_media": false,
      "is_source": true,
      "is_script": true,
      "licenses": [],
      "license_expressions": [],
      "percentage_of_license_text": 0,
      "copyrights": [],
      "holders": [],
      "authors": [],
      "files_count": 0,
      "dirs_count": 0,
      "size_count": 0,
      "scan_errors": []
    },
    {
      "path": ".github",
      "type": "directory",
      "name": ".github",
      "base_name": ".github",
      "extension": "",
      "size": 0,
      "date": null,
      "sha1": null,
      "md5": null,
      "sha256": null,
      "mime_type": null,
      "file_type": null,
      "programming_language": null,
      "is_binary": false,
      "is_text": false,
      "is_archive": false,
      "is_media": false,
      "is_source": false,
      "is_script": false,
      "licenses": [],
      "license_expressions": [],
      "percentage_of_license_text": 0,
      "copyrights": [],
      "holders": [],
      "authors": [],
      "files_count": 1,
      "dirs_count": 1,
      "size_count": 2526,
      "scan_errors": []
    },
    {
      "path": ".github/workflows",
      "type": "directory",
      "name": "workflows",
      "base_name": "workflows",
      "extension": "",
      "size": 0,
      "date": null,
      "sha1": null,
      "md5": null,
      "sha256": null,
      "mime_type": null,
      "file_type": null,
      "programming_language": null,
      "is_binary": false,
      "is_text": false,
      "is_archive": false,
      "is_media": false,
      "is_source": false,
      "is_script": false,
      "licenses": [],
      "license_expressions": [],
      "percentage_of_license_text": 0,
      "copyrights": [],
      "holders": [],
      "authors": [],
      "files_count": 1,
      "dirs_count": 0,
      "size_count": 2526,
      "scan_errors": []
    },
    {
      "path": ".github/workflows/main.yml",
      "type": "file",
      "name": "main.yml",
      "base_name": "main",
      "extension": ".yml",
      "size": 2526,
      "date": "2020-11-24",
      "sha1": "6d5d46a8fbe3d38cd57ad29d7af061ae0eca4976",
      "md5": "d24373aa3d49f315c8063c866b8c64ac",
      "sha256": "7234a2e7e0b2d9bbab264b47fd630b52d707b1385beddcdc096583176b6dc1f7",
      "mime_type": "text/plain",
      "file_type": "ASCII text",
      "programming_language": "ActionScript 3",
      "is_binary": false,
      "is_text": true,
      "is_archive": false,
      "is_media": false,
      "is_source": true,
      "is_script": false,
      "licenses": [],
      "license_expressions": [],
      "percentage_of_license_text": 0,
      "copyrights": [],
      "holders": [],
      "authors": [],
      "files_count": 0,
      "dirs_count": 0,
      "size_count": 0,
      "scan_errors": []
    },
    {
      "path": "docs",
      "type": "directory",
      "name": "docs",
      "base_name": "docs",
      "extension": "",
      "size": 0,
      "date": null,
      "sha1": null,
      "md5": null,
      "sha256": null,
      "mime_type": null,
      "file_type": null,
      "programming_language": null,
      "is_binary": false,
      "is_text": false,
      "is_archive": false,
      "is_media": false,
      "is_source": false,
      "is_script": false,
      "licenses": [],
      "license_expressions": [],
      "percentage_of_license_text": 0,
      "copyrights": [],
      "holders": [],
      "authors": [],
      "files_count": 5,
      "dirs_count": 0,
      "size_count": 25142,
      "scan_errors": []
    },
    {
      "path": "docs/changelog.rst",
      "type": "file",
      "name": "changelog.rst",
      "base_name": "changelog",
      "extension": ".rst",
      "size": 5289,
      "date": "2020-11-24",
      "sha1": "a32293ba7b9449db2964f1b10decef1651935e20",
      "md5": "f0212207aa02f6c280bd1b0e33ecd984",
      "sha256": "2c168ce3790b1e8af25b1d355b7c98a4b310c2ac1a1e05eccd33c7ab5374e235",
      "mime_type": "text/plain",
      "file_type": "ReStructuredText file, ASCII text",
      "programming_language": null,
      "is_binary": false,
      "is_text": true,
      "is_archive": false,
      "is_media": false,
      "is_source": false,
      "is_script": false,
      "licenses": [],
      "license_expressions": [],
      "percentage_of_license_text": 0,
      "copyrights": [],
      "holders": [],
      "authors": [],
      "files_count": 0,
      "dirs_count": 0,
      "size_count": 0,
      "scan_errors": []
    },
    {
      "path": "docs/conf.py",
      "type": "file",
      "name": "conf.py",
      "base_name": "conf",
      "extension": ".py",
      "size": 4177,
      "date": "2020-11-24",
      "sha1": "d7381a23f4e9d78654438f4c4dfe61b1f13d1e56",
      "md5": "4d274ec73bf58aebd148bf49e26f2c75",
      "sha256": "1a6cf39c72a1b531d08e370895c4319212520e836e2efda34ebaad020e1d858d",
      "mime_type": "text/plain",
      "file_type": "ASCII text",
      "programming_language": "Python",
      "is_binary": false,
      "is_text": true,
      "is_archive": false,
      "is_media": false,
      "is_source": true,
      "is_script": false,
      "licenses": [],
      "license_expressions": [],
      "percentage_of_license_text": 0,
      "copyrights": [
        {
          "value": "copyright 2017-2019, Brett Cannon, Barry Warsaw",
          "start_line": 24,
          "end_line": 24
        }
      ],
      "holders": [
        {
          "value": "Brett Cannon, Barry Warsaw",
          "start_line": 24,
          "end_line": 24
        }
      ],
      "authors": [],
      "files_count": 0,
      "dirs_count": 0,
      "size_count": 0,
      "scan_errors": []
    },
    {
      "path": "docs/index.rst",
      "type": "file",
      "name": "index.rst",
      "base_name": "index",
      "extension": ".rst",
      "size": 1734,
      "date": "2020-11-24",
      "sha1": "f9169cae38e6d4063be06123f45876795f2d2d47",
      "md5": "487c7505e60fe2787a452351b268461c",
      "sha256": "063d929894210a70b7effd577d1db4fcb05c44217f34ea93762bff1f56c5e220",
      "mime_type": "text/plain",
      "file_type": "ReStructuredText file, ASCII text",
      "programming_language": null,
      "is_binary": false,
      "is_text": true,
      "is_archive": false,
      "is_media": false,
      "is_source": false,
      "is_script": false,
      "licenses": [],
      "license_expressions": [],
      "percentage_of_license_text": 0,
      "copyrights": [],
      "holders": [],
      "authors": [],
      "files_count": 0,
      "dirs_count": 0,
      "size_count": 0,
      "scan_errors": []
    },
    {
      "path": "docs/migration.rst",
      "type": "file",
      "name": "migration.rst",
      "base_name": "migration",
      "extension": ".rst",
      "size": 5907,
      "date": "2020-11-24",
      "sha1": "321b22791b5fb8bd5fab480958f1fd3a743eb192",
      "md5": "145868ee34ca646041e1698770537df1",
      "sha256": "84de3619ce1c3b4e84e5457241eeafd9cdbe5e63120d4996c47be56bf5dfbdc3",
      "mime_type": "text/plain",
      "file_type": "ReStructuredText file, ASCII text",
      "programming_language": null,
      "is_binary": false,
      "is_text": true,
      "is_archive": false,
      "is_media": false,
      "is_source": false,
      "is_script": false,
      "licenses": [],
      "license_expressions": [],
      "percentage_of_license_text": 0,
      "copyrights": [],
      "holders": [],
      "authors": [],
      "files_count": 0,
      "dirs_count": 0,
      "size_count": 0,
      "scan_errors": []
    },
    {
      "path": "docs/using.rst",
      "type": "file",
      "name": "using.rst",
      "base_name": "using",
      "extension": ".rst",
      "size": 8035,
      "date": "2020-11-24",
      "sha1": "055697620fa7c6a1e8a43fea4784924550d5200d",
      "md5": "8b70ee79440915ae506515d9c98ca4fa",
      "sha256": "a71f39902282c3104eab339ef123dc7b052767925c9dfa29cbdbf8dbabf1718f",
      "mime_type": "text/plain",
      "file_type": "ReStructuredText file, ASCII text",
      "programming_language": "Python",
      "is_binary": false,
      "is_text": true,
      "is_archive": false,
      "is_media": false,
      "is_source": false,
      "is_script": false,
      "licenses": [],
      "license_expressions": [],
      "percentage_of_license_text": 0,
      "copyrights": [],
      "holders": [],
      "authors": [],
      "files_count": 0,
      "dirs_count": 0,
      "size_count": 0,
      "scan_errors": []
    },
    {
      "path": "importlib_resources",
      "type": "directory",
      "name": "importlib_resources",
      "base_name": "importlib_resources",
      "extension": "",
      "size": 0,
      "date": null,
      "sha1": null,
      "md5": null,
      "sha256": null,
      "mime_type": null,
      "file_type": null,
      "programming_language": null,
      "is_binary": false,
      "is_text": false,
      "is_archive": false,
      "is_media": false,
      "is_source": false,
      "is_script": false,
      "licenses": [],
      "license_expressions": [],
      "percentage_of_license_text": 0,
      "copyrights": [],
      "holders": [],
      "authors": [],
      "files_count": 37,
      "dirs_count": 9,
      "size_count": 55442,
      "scan_errors": []
    },
    {
      "path": "importlib_resources/__init__.py",
      "type": "file",
      "name": "__init__.py",
      "base_name": "__init__",
      "extension": ".py",
      "size": 977,
      "date": "2020-11-24",
      "sha1": "70e85b8d17df601072f490f0cdf6ee7d43e8ff15",
      "md5": "0305e35c3bf1797247502788f9924a1d",
      "sha256": "86cc0398b007d085252d6c267475cf3769a0bacd9b9392300cff8117383b54aa",
      "mime_type": "text/plain",
      "file_type": "Python script, ASCII text executable",
      "programming_language": "Python",
      "is_binary": false,
      "is_text": true,
      "is_archive": false,
      "is_media": false,
      "is_source": true,
      "is_script": true,
      "licenses": [],
      "license_expressions": [],
      "percentage_of_license_text": 0,
      "copyrights": [],
      "holders": [],
      "authors": [],
      "files_count": 0,
      "dirs_count": 0,
      "size_count": 0,
      "scan_errors": []
    },
    {
      "path": "importlib_resources/_common.py",
      "type": "file",
      "name": "_common.py",
      "base_name": "_common",
      "extension": ".py",
      "size": 3121,
      "date": "2020-11-24",
      "sha1": "74d654ba28a957f8bb49d49a4830fa62066841a5",
      "md5": "dbe2b442d4a59da4a09c6b07b01eb07f",
      "sha256": "44df1c5ce66d97282f95bc937b077e9e2f700b58705e97db667ae5ee46f1d272",
      "mime_type": "text/x-python",
      "file_type": "Python script text executable Python script, ASCII text executable",
      "programming_language": "Python",
      "is_binary": false,
      "is_text": true,
      "is_archive": false,
      "is_media": false,
      "is_source": true,
      "is_script": true,
      "licenses": [],
      "license_expressions": [],
      "percentage_of_license_text": 0,
      "copyrights": [],
      "holders": [],
      "authors": [],
      "files_count": 0,
      "dirs_count": 0,
      "size_count": 0,
      "scan_errors": []
    },
    {
      "path": "importlib_resources/_compat.py",
      "type": "file",
      "name": "_compat.py",
      "base_name": "_compat",
      "extension": ".py",
      "size": 3694,
      "date": "2020-11-24",
      "sha1": "0a83286f39edbedf299f9c2eea3710472362a97e",
      "md5": "3fa78a484ae92b67d4c30c80d869dd2a",
      "sha256": "34309739fd74f7b683249c7efe943450892dcd5c761b568f2104d1146c741472",
      "mime_type": "text/x-python",
      "file_type": "Python script, ASCII text executable",
      "programming_language": "Python",
      "is_binary": false,
      "is_text": true,
      "is_archive": false,
      "is_media": false,
      "is_source": true,
      "is_script": true,
      "licenses": [],
      "license_expressions": [],
      "percentage_of_license_text": 0,
      "copyrights": [],
      "holders": [],
      "authors": [],
      "files_count": 0,
      "dirs_count": 0,
      "size_count": 0,
      "scan_errors": []
    },
    {
      "path": "importlib_resources/_py2.py",
      "type": "file",
      "name": "_py2.py",
      "base_name": "_py2",
      "extension": ".py",
      "size": 4146,
      "date": "2020-11-24",
      "sha1": "8651ddfcd07e76cca41bcf05c1572122d80ec5af",
      "md5": "d755f02324ce7aecc0313b6d265445d8",
      "sha256": "1bd3399afd482e5f0d01119d357d2ff7f17f1dbe0750a092f8508d2badc08efc",
      "mime_type": "text/x-python",
      "file_type": "Python script, ASCII text executable",
      "programming_language": "Python",
      "is_binary": false,
      "is_text": true,
      "is_archive": false,
      "is_media": false,
      "is_source": true,
      "is_script": true,
      "licenses": [],
      "license_expressions": [],
      "percentage_of_license_text": 0,
      "copyrights": [],
      "holders": [],
      "authors": [],
      "files_count": 0,
      "dirs_count": 0,
      "size_count": 0,
      "scan_errors": []
    },
    {
      "path": "importlib_resources/_py3.py",
      "type": "file",
      "name": "_py3.py",
      "base_name": "_py3",
      "extension": ".py",
      "size": 5564,
      "date": "2020-11-24",
      "sha1": "d1d9a99929869e9ccb08092eafcc3502c7fb6582",
      "md5": "70f43e390481392fa0a1b99c0cd63c05",
      "sha256": "05cfa9d1461f3d5597149db51cb35f56f6d5acf2455c103483cd2ba8f22792af",
      "mime_type": "text/x-python",
      "file_type": "Python script, ASCII text executable",
      "programming_language": "Python",
      "is_binary": false,
      "is_text": true,
      "is_archive": false,
      "is_media": false,
      "is_source": true,
      "is_script": true,
      "licenses": [],
      "license_expressions": [],
      "percentage_of_license_text": 0,
      "copyrights": [],
      "holders": [],
      "authors": [],
      "files_count": 0,
      "dirs_count": 0,
      "size_count": 0,
      "scan_errors": []
    },
    {
      "path": "importlib_resources/abc.py",
      "type": "file",
      "name": "abc.py",
      "base_name": "abc",
      "extension": ".py",
      "size": 3894,
      "date": "2020-11-24",
      "sha1": "f224cb845d69f94b7c2af03448171fe001caf026",
      "md5": "03d1bdbc2a550c4e049c562f759dcf95",
      "sha256": "e8f5f8369aefdfd627021b773729a11c8b92b28d287002aa0c965ff80e81808c",
      "mime_type": "text/x-python",
      "file_type": "Python script, ASCII text executable",
      "programming_language": "Python",
      "is_binary": false,
      "is_text": true,
      "is_archive": false,
      "is_media": false,
      "is_source": true,
      "is_script": true,
      "licenses": [],
      "license_expressions": [],
      "percentage_of_license_text": 0,
      "copyrights": [],
      "holders": [],
      "authors": [],
      "files_count": 0,
      "dirs_count": 0,
      "size_count": 0,
      "scan_errors": []
    },
    {
      "path": "importlib_resources/py.typed",
      "type": "file",
      "name": "py.typed",
      "base_name": "py",
      "extension": ".typed",
      "size": 0,
      "date": "2020-11-24",
      "sha1": null,
      "md5": null,
      "sha256": null,
      "mime_type": "inode/x-empty",
      "file_type": "empty",
      "programming_language": null,
      "is_binary": false,
      "is_text": true,
      "is_archive": false,
      "is_media": false,
      "is_source": false,
      "is_script": false,
      "licenses": [],
      "license_expressions": [],
      "percentage_of_license_text": 0,
      "copyrights": [],
      "holders": [],
      "authors": [],
      "files_count": 0,
      "dirs_count": 0,
      "size_count": 0,
      "scan_errors": []
    },
    {
      "path": "importlib_resources/readers.py",
      "type": "file",
      "name": "readers.py",
      "base_name": "readers",
      "extension": ".py",
      "size": 3674,
      "date": "2020-11-24",
      "sha1": "4ee8e241e8906c7e4ed3207a50f22073f650f996",
      "md5": "f3afd1ed93ef064c577fe16779410a59",
      "sha256": "7c6b9206831e78445456bb1c37d1ab869d2cfb028ccbb9cc55b0b1f76bc8946b",
      "mime_type": "text/x-python",
      "file_type": "Python script, ASCII text executable",
      "programming_language": "Python",
      "is_binary": false,
      "is_text": true,
      "is_archive": false,
      "is_media": false,
      "is_source": true,
      "is_script": true,
      "licenses": [],
      "license_expressions": [],
      "percentage_of_license_text": 0,
      "copyrights": [],
      "holders": [],
      "authors": [],
      "files_count": 0,
      "dirs_count": 0,
      "size_count": 0,
      "scan_errors": []
    },
    {
      "path": "importlib_resources/trees.py",
      "type": "file",
      "name": "trees.py",
      "base_name": "trees",
      "extension": ".py",
      "size": 117,
      "date": "2020-11-24",
      "sha1": "ac5d24a3bb8cfd452272fa288b99d856967fa6aa",
      "md5": "12e064ffa145f6703a0486f3e9c04e85",
      "sha256": "537165412239fbe785e007733a306f5b8c678cbdb53855fc8af93cd90bb0bff3",
      "mime_type": "text/x-python",
      "file_type": "Python script, ASCII text executable",
      "programming_language": "Python",
      "is_binary": false,
      "is_text": true,
      "is_archive": false,
      "is_media": false,
      "is_source": true,
      "is_script": true,
      "licenses": [],
      "license_expressions": [],
      "percentage_of_license_text": 0,
      "copyrights": [],
      "holders": [],
      "authors": [],
      "files_count": 0,
      "dirs_count": 0,
      "size_count": 0,
      "scan_errors": []
    },
    {
      "path": "importlib_resources/tests",
      "type": "directory",
      "name": "tests",
      "base_name": "tests",
      "extension": "",
      "size": 0,
      "date": null,
      "sha1": null,
      "md5": null,
      "sha256": null,
      "mime_type": null,
      "file_type": null,
      "programming_language": null,
      "is_binary": false,
      "is_text": false,
      "is_archive": false,
      "is_media": false,
      "is_source": false,
      "is_script": false,
      "licenses": [],
      "license_expressions": [],
      "percentage_of_license_text": 0,
      "copyrights": [],
      "holders": [],
      "authors": [],
      "files_count": 28,
      "dirs_count": 8,
      "size_count": 30255,
      "scan_errors": []
    },
    {
      "path": "importlib_resources/tests/__init__.py",
      "type": "file",
      "name": "__init__.py",
      "base_name": "__init__",
      "extension": ".py",
      "size": 0,
      "date": "2020-11-24",
      "sha1": null,
      "md5": null,
      "sha256": null,
      "mime_type": "inode/x-empty",
      "file_type": "empty",
      "programming_language": "Python",
      "is_binary": false,
      "is_text": true,
      "is_archive": false,
      "is_media": false,
      "is_source": true,
      "is_script": false,
      "licenses": [],
      "license_expressions": [],
      "percentage_of_license_text": 0,
      "copyrights": [],
      "holders": [],
      "authors": [],
      "files_count": 0,
      "dirs_count": 0,
      "size_count": 0,
      "scan_errors": []
    },
    {
      "path": "importlib_resources/tests/_compat.py",
      "type": "file",
      "name": "_compat.py",
      "base_name": "_compat",
      "extension": ".py",
      "size": 801,
      "date": "2020-11-24",
      "sha1": "3776407172b790b6f7b03bde4e4f436737b870a8",
      "md5": "2034e989473a599912fc63a3587a474a",
      "sha256": "81e29625ef141978c2d7cd49c66b7147703fa3956b478cb1a254b4c5b9f1325c",
      "mime_type": "text/x-python",
      "file_type": "Python script, ASCII text executable",
      "programming_language": "Python",
      "is_binary": false,
      "is_text": true,
      "is_archive": false,
      "is_media": false,
      "is_source": true,
      "is_script": true,
      "licenses": [],
      "license_expressions": [],
      "percentage_of_license_text": 0,
      "copyrights": [],
      "holders": [],
      "authors": [],
      "files_count": 0,
      "dirs_count": 0,
      "size_count": 0,
      "scan_errors": []
    },
    {
      "path": "importlib_resources/tests/py27compat.py",
      "type": "file",
      "name": "py27compat.py",
      "base_name": "py27compat",
      "extension": ".py",
      "size": 965,
      "date": "2020-11-24",
      "sha1": "611772d82f8ae72761149aaa0631bfc1cebad7c0",
      "md5": "72115ced1f7351435d1963f70db31023",
      "sha256": "f650c9906576b303d540983a8ac3a8ad13455ae3fa29ea167780f66c5366ccb2",
      "mime_type": "text/x-python",
      "file_type": "Python script, ASCII text executable",
      "programming_language": "Python",
      "is_binary": false,
      "is_text": true,
      "is_archive": false,
      "is_media": false,
      "is_source": true,
      "is_script": true,
      "licenses": [],
      "license_expressions": [],
      "percentage_of_license_text": 0,
      "copyrights": [],
      "holders": [],
      "authors": [],
      "files_count": 0,
      "dirs_count": 0,
      "size_count": 0,
      "scan_errors": []
    },
    {
      "path": "importlib_resources/tests/test_files.py",
      "type": "file",
      "name": "test_files.py",
      "base_name": "test_files",
      "extension": ".py",
      "size": 1017,
      "date": "2020-11-24",
      "sha1": "3766e4772763393139093501f95b2d0f6bc4fb54",
      "md5": "1bd23db84375196505ffb86530dfe80e",
      "sha256": "f75adfe02ef8fda26c28d4adf9afb4dec955a58f50480b826e88055a7b1a3e31",
      "mime_type": "text/plain",
      "file_type": "Python script, ASCII text executable",
      "programming_language": "Python",
      "is_binary": false,
      "is_text": true,
      "is_archive": false,
      "is_media": false,
      "is_source": true,
      "is_script": true,
      "licenses": [],
      "license_expressions": [],
      "percentage_of_license_text": 0,
      "copyrights": [],
      "holders": [],
      "authors": [],
      "files_count": 0,
      "dirs_count": 0,
      "size_count": 0,
      "scan_errors": []
    },
    {
      "path": "importlib_resources/tests/test_open.py",
      "type": "file",
      "name": "test_open.py",
      "base_name": "test_open",
      "extension": ".py",
      "size": 2565,
      "date": "2020-11-24",
      "sha1": "937c838a208ea97c3a28b98ddc912f09e6b58930",
      "md5": "9332a0717e86eb2a28ccbc0da46bb4a2",
      "sha256": "a48616bee4c3a50389297d1212e38a1a8b6cb19704798ff134f0ea2c60af3ff5",
      "mime_type": "text/plain",
      "file_type": "Python script, ASCII text executable",
      "programming_language": "Python",
      "is_binary": false,
      "is_text": true,
      "is_archive": false,
      "is_media": false,
      "is_source": true,
      "is_script": true,
      "licenses": [],
      "license_expressions": [],
      "percentage_of_license_text": 0,
      "copyrights": [],
      "holders": [],
      "authors": [],
      "files_count": 0,
      "dirs_count": 0,
      "size_count": 0,
      "scan_errors": []
    },
    {
      "path": "importlib_resources/tests/test_path.py",
      "type": "file",
      "name": "test_path.py",
      "base_name": "test_path",
      "extension": ".py",
      "size": 1548,
      "date": "2020-11-24",
      "sha1": "470ea80a234d19ba7397b391b001114602ce8275",
      "md5": "0dd999dedd11c47f118de054c6ef9c33",
      "sha256": "1a750ebbedf7f28f687df9c2f31c1b5e31fd248409a43ec9ba3810906075d3a4",
      "mime_type": "text/plain",
      "file_type": "Python script, ASCII text executable",
      "programming_language": "Python",
      "is_binary": false,
      "is_text": true,
      "is_archive": false,
      "is_media": false,
      "is_source": true,
      "is_script": true,
      "licenses": [],
      "license_expressions": [],
      "percentage_of_license_text": 0,
      "copyrights": [],
      "holders": [],
      "authors": [],
      "files_count": 0,
      "dirs_count": 0,
      "size_count": 0,
      "scan_errors": []
    },
    {
      "path": "importlib_resources/tests/test_read.py",
      "type": "file",
      "name": "test_read.py",
      "base_name": "test_read",
      "extension": ".py",
      "size": 2046,
      "date": "2020-11-24",
      "sha1": "1e5e976471a14f71087b046d863d4a618f616c92",
      "md5": "0582383b46d7032fb6a9cdf61c3f3ca8",
      "sha256": "0e903bb73c52425534fd842e5a26c1dc4e4f0cbf5f41477378aa045069c0c7bf",
      "mime_type": "text/plain",
      "file_type": "Python script, ASCII text executable",
      "programming_language": "Python",
      "is_binary": false,
      "is_text": true,
      "is_archive": false,
      "is_media": false,
      "is_source": true,
      "is_script": true,
      "licenses": [],
      "license_expressions": [],
      "percentage_of_license_text": 0,
      "copyrights": [],
      "holders": [],
      "authors": [],
      "files_count": 0,
      "dirs_count": 0,
      "size_count": 0,
      "scan_errors": []
    },
    {
      "path": "importlib_resources/tests/test_reader.py",
      "type": "file",
      "name": "test_reader.py",
      "base_name": "test_reader",
      "extension": ".py",
      "size": 4638,
      "date": "2020-11-24",
      "sha1": "b67a4a58d548e8dc85d62772fd4ffd775812dae4",
      "md5": "7380dfcb1618584eea173842f6021802",
      "sha256": "c843b4c72ad80dc1919ac042e80d67f7d19789366956fa7eb86037d77b3a69aa",
      "mime_type": "text/x-python",
      "file_type": "Python script, ASCII text executable",
      "programming_language": "Python",
      "is_binary": false,
      "is_text": true,
      "is_archive": false,
      "is_media": false,
      "is_source": true,
      "is_script": true,
      "licenses": [],
      "license_expressions": [],
      "percentage_of_license_text": 0,
      "copyrights": [],
      "holders": [],
      "authors": [],
      "files_count": 0,
      "dirs_count": 0,
      "size_count": 0,
      "scan_errors": []
    },
    {
      "path": "importlib_resources/tests/test_resource.py",
      "type": "file",
      "name": "test_resource.py",
      "base_name": "test_resource",
      "extension": ".py",
      "size": 8766,
      "date": "2020-11-24",
      "sha1": "f1adbf68b7df31a11e60553b42976475ec555f0d",
      "md5": "6ef2c76e9c87a2d707a3b872e48ce0d4",
      "sha256": "19bacc78727be0de8a246dfc4c3a1d0a9fbe9ec4671475c973b36b004a943da5",
      "mime_type": "text/x-python",
      "file_type": "Python script, ASCII text executable",
      "programming_language": "Python",
      "is_binary": false,
      "is_text": true,
      "is_archive": false,
      "is_media": false,
      "is_source": true,
      "is_script": true,
      "licenses": [],
      "license_expressions": [],
      "percentage_of_license_text": 0,
      "copyrights": [],
      "holders": [],
      "authors": [],
      "files_count": 0,
      "dirs_count": 0,
      "size_count": 0,
      "scan_errors": []
    },
    {
      "path": "importlib_resources/tests/util.py",
      "type": "file",
      "name": "util.py",
      "base_name": "util",
      "extension": ".py",
      "size": 5914,
      "date": "2020-11-24",
      "sha1": "71d64646f5bbb0f8956957a8cdbf5e62bb454401",
      "md5": "a9e40a8faeefa63be6f629fd57d7f0e8",
      "sha256": "f21045c2a21944914dbe46e8101eda5ac0aa4ed8148e5588fe2434295d79f189",
      "mime_type": "text/x-python",
      "file_type": "Python script, ASCII text executable",
      "programming_language": "Python",
      "is_binary": false,
      "is_text": true,
      "is_archive": false,
      "is_media": false,
      "is_source": true,
      "is_script": true,
      "licenses": [],
      "license_expressions": [],
      "percentage_of_license_text": 0,
      "copyrights": [],
      "holders": [],
      "authors": [],
      "files_count": 0,
      "dirs_count": 0,
      "size_count": 0,
      "scan_errors": []
    },
    {
      "path": "importlib_resources/tests/data01",
      "type": "directory",
      "name": "data01",
      "base_name": "data01",
      "extension": "",
      "size": 0,
      "date": null,
      "sha1": null,
      "md5": null,
      "sha256": null,
      "mime_type": null,
      "file_type": null,
      "programming_language": null,
      "is_binary": false,
      "is_text": false,
      "is_archive": false,
      "is_media": false,
      "is_source": false,
      "is_script": false,
      "licenses": [],
      "license_expressions": [],
      "percentage_of_license_text": 0,
      "copyrights": [],
      "holders": [],
      "authors": [],
      "files_count": 6,
      "dirs_count": 1,
      "size_count": 72,
      "scan_errors": []
    },
    {
      "path": "importlib_resources/tests/data01/__init__.py",
      "type": "file",
      "name": "__init__.py",
      "base_name": "__init__",
      "extension": ".py",
      "size": 0,
      "date": "2020-11-24",
      "sha1": null,
      "md5": null,
      "sha256": null,
      "mime_type": "inode/x-empty",
      "file_type": "empty",
      "programming_language": "Python",
      "is_binary": false,
      "is_text": true,
      "is_archive": false,
      "is_media": false,
      "is_source": true,
      "is_script": false,
      "licenses": [],
      "license_expressions": [],
      "percentage_of_license_text": 0,
      "copyrights": [],
      "holders": [],
      "authors": [],
      "files_count": 0,
      "dirs_count": 0,
      "size_count": 0,
      "scan_errors": []
    },
    {
      "path": "importlib_resources/tests/data01/binary.file",
      "type": "file",
      "name": "binary.file",
      "base_name": "binary",
      "extension": ".file",
      "size": 4,
      "date": "2020-11-24",
      "sha1": "a02a05b025b928c039cf1ae7e8ee04e7c190c0db",
      "md5": "37b59afd592725f9305e484a5d7f5168",
      "sha256": "054edec1d0211f624fed0cbca9d4f9400b0e491c43742af2c5b0abebf0c990d8",
      "mime_type": "application/octet-stream",
      "file_type": "data",
      "programming_language": null,
      "is_binary": true,
      "is_text": false,
      "is_archive": false,
      "is_media": false,
      "is_source": false,
      "is_script": false,
      "licenses": [],
      "license_expressions": [],
      "percentage_of_license_text": 0,
      "copyrights": [],
      "holders": [],
      "authors": [],
      "files_count": 0,
      "dirs_count": 0,
      "size_count": 0,
      "scan_errors": []
    },
    {
      "path": "importlib_resources/tests/data01/utf-16.file",
      "type": "file",
      "name": "utf-16.file",
      "base_name": "utf-16",
      "extension": ".file",
      "size": 44,
      "date": "2020-11-24",
      "sha1": "3bf88b182117dce769d0cb03fb14ab771f827649",
      "md5": "ff6357f0940465f479305cbe0ba8f78f",
      "sha256": "b79abdaa1c57d2b62a22d04e33c0f7ca5c06f911eb9ce62d7932ed42beac17b8",
      "mime_type": "text/plain",
      "file_type": "Little-endian UTF-16 Unicode text",
      "programming_language": null,
      "is_binary": false,
      "is_text": true,
      "is_archive": false,
      "is_media": false,
      "is_source": false,
      "is_script": false,
      "licenses": [],
      "license_expressions": [],
      "percentage_of_license_text": 0,
      "copyrights": [],
      "holders": [],
      "authors": [],
      "files_count": 0,
      "dirs_count": 0,
      "size_count": 0,
      "scan_errors": []
    },
    {
      "path": "importlib_resources/tests/data01/utf-8.file",
      "type": "file",
      "name": "utf-8.file",
      "base_name": "utf-8",
      "extension": ".file",
      "size": 20,
      "date": "2020-11-24",
      "sha1": "7e13931923104bda5ae0fe40db20d0aaf51610f9",
      "md5": "58da4ec0dd953291e42b4a78598913da",
      "sha256": "9305a0606e3243e645d97fd603ae848d83e6c49467fb0f1a48e892f5ef2d2986",
      "mime_type": "text/plain",
      "file_type": "ASCII text",
      "programming_language": null,
      "is_binary": false,
      "is_text": true,
      "is_archive": false,
      "is_media": false,
      "is_source": false,
      "is_script": false,
      "licenses": [],
      "license_expressions": [],
      "percentage_of_license_text": 0,
      "copyrights": [],
      "holders": [],
      "authors": [],
      "files_count": 0,
      "dirs_count": 0,
      "size_count": 0,
      "scan_errors": []
    },
    {
      "path": "importlib_resources/tests/data01/subdirectory",
      "type": "directory",
      "name": "subdirectory",
      "base_name": "subdirectory",
      "extension": "",
      "size": 0,
      "date": null,
      "sha1": null,
      "md5": null,
      "sha256": null,
      "mime_type": null,
      "file_type": null,
      "programming_language": null,
      "is_binary": false,
      "is_text": false,
      "is_archive": false,
      "is_media": false,
      "is_source": false,
      "is_script": false,
      "licenses": [],
      "license_expressions": [],
      "percentage_of_license_text": 0,
      "copyrights": [],
      "holders": [],
      "authors": [],
      "files_count": 2,
      "dirs_count": 0,
      "size_count": 4,
      "scan_errors": []
    },
    {
      "path": "importlib_resources/tests/data01/subdirectory/__init__.py",
      "type": "file",
      "name": "__init__.py",
      "base_name": "__init__",
      "extension": ".py",
      "size": 0,
      "date": "2020-11-24",
      "sha1": null,
      "md5": null,
      "sha256": null,
      "mime_type": "inode/x-empty",
      "file_type": "empty",
      "programming_language": "Python",
      "is_binary": false,
      "is_text": true,
      "is_archive": false,
      "is_media": false,
      "is_source": true,
      "is_script": false,
      "licenses": [],
      "license_expressions": [],
      "percentage_of_license_text": 0,
      "copyrights": [],
      "holders": [],
      "authors": [],
      "files_count": 0,
      "dirs_count": 0,
      "size_count": 0,
      "scan_errors": []
    },
    {
      "path": "importlib_resources/tests/data01/subdirectory/binary.file",
      "type": "file",
      "name": "binary.file",
      "base_name": "binary",
      "extension": ".file",
      "size": 4,
      "date": "2020-11-24",
      "sha1": "a02a05b025b928c039cf1ae7e8ee04e7c190c0db",
      "md5": "37b59afd592725f9305e484a5d7f5168",
      "sha256": "054edec1d0211f624fed0cbca9d4f9400b0e491c43742af2c5b0abebf0c990d8",
      "mime_type": "application/octet-stream",
      "file_type": "data",
      "programming_language": null,
      "is_binary": true,
      "is_text": false,
      "is_archive": false,
      "is_media": false,
      "is_source": false,
      "is_script": false,
      "licenses": [],
      "license_expressions": [],
      "percentage_of_license_text": 0,
      "copyrights": [],
      "holders": [],
      "authors": [],
      "files_count": 0,
      "dirs_count": 0,
      "size_count": 0,
      "scan_errors": []
    },
    {
      "path": "importlib_resources/tests/data02",
      "type": "directory",
      "name": "data02",
      "base_name": "data02",
      "extension": "",
      "size": 0,
      "date": null,
      "sha1": null,
      "md5": null,
      "sha256": null,
      "mime_type": null,
      "file_type": null,
      "programming_language": null,
      "is_binary": false,
      "is_text": false,
      "is_archive": false,
      "is_media": false,
      "is_source": false,
      "is_script": false,
      "licenses": [],
      "license_expressions": [],
      "percentage_of_license_text": 0,
      "copyrights": [],
      "holders": [],
      "authors": [],
      "files_count": 5,
      "dirs_count": 2,
      "size_count": 26,
      "scan_errors": []
    },
    {
      "path": "importlib_resources/tests/data02/__init__.py",
      "type": "file",
      "name": "__init__.py",
      "base_name": "__init__",
      "extension": ".py",
      "size": 0,
      "date": "2020-11-24",
      "sha1": null,
      "md5": null,
      "sha256": null,
      "mime_type": "inode/x-empty",
      "file_type": "empty",
      "programming_language": "Python",
      "is_binary": false,
      "is_text": true,
      "is_archive": false,
      "is_media": false,
      "is_source": true,
      "is_script": false,
      "licenses": [],
      "license_expressions": [],
      "percentage_of_license_text": 0,
      "copyrights": [],
      "holders": [],
      "authors": [],
      "files_count": 0,
      "dirs_count": 0,
      "size_count": 0,
      "scan_errors": []
    },
    {
      "path": "importlib_resources/tests/data02/one",
      "type": "directory",
      "name": "one",
      "base_name": "one",
      "extension": "",
      "size": 0,
      "date": null,
      "sha1": null,
      "md5": null,
      "sha256": null,
      "mime_type": null,
      "file_type": null,
      "programming_language": null,
      "is_binary": false,
      "is_text": false,
      "is_archive": false,
      "is_media": false,
      "is_source": false,
      "is_script": false,
      "licenses": [],
      "license_expressions": [],
      "percentage_of_license_text": 0,
      "copyrights": [],
      "holders": [],
      "authors": [],
      "files_count": 2,
      "dirs_count": 0,
      "size_count": 13,
      "scan_errors": []
    },
    {
      "path": "importlib_resources/tests/data02/one/__init__.py",
      "type": "file",
      "name": "__init__.py",
      "base_name": "__init__",
      "extension": ".py",
      "size": 0,
      "date": "2020-11-24",
      "sha1": null,
      "md5": null,
      "sha256": null,
      "mime_type": "inode/x-empty",
      "file_type": "empty",
      "programming_language": "Python",
      "is_binary": false,
      "is_text": true,
      "is_archive": false,
      "is_media": false,
      "is_source": true,
      "is_script": false,
      "licenses": [],
      "license_expressions": [],
      "percentage_of_license_text": 0,
      "copyrights": [],
      "holders": [],
      "authors": [],
      "files_count": 0,
      "dirs_count": 0,
      "size_count": 0,
      "scan_errors": []
    },
    {
      "path": "importlib_resources/tests/data02/one/resource1.txt",
      "type": "file",
      "name": "resource1.txt",
      "base_name": "resource1",
      "extension": ".txt",
      "size": 13,
      "date": "2020-11-24",
      "sha1": "ed4e65535f88b0c0fbe44d3bff1bf115f458b567",
      "md5": "38a86d547d45a7aee6d26f6506635960",
      "sha256": "d747e529a73b73e5d7173277b7e001e4c263941cbffdd499bcf13f74e9b6aba5",
      "mime_type": "text/plain",
      "file_type": "ASCII text",
      "programming_language": null,
      "is_binary": false,
      "is_text": true,
      "is_archive": false,
      "is_media": false,
      "is_source": false,
      "is_script": false,
      "licenses": [],
      "license_expressions": [],
      "percentage_of_license_text": 0,
      "copyrights": [],
      "holders": [],
      "authors": [],
      "files_count": 0,
      "dirs_count": 0,
      "size_count": 0,
      "scan_errors": []
    },
    {
      "path": "importlib_resources/tests/data02/two",
      "type": "directory",
      "name": "two",
      "base_name": "two",
      "extension": "",
      "size": 0,
      "date": null,
      "sha1": null,
      "md5": null,
      "sha256": null,
      "mime_type": null,
      "file_type": null,
      "programming_language": null,
      "is_binary": false,
      "is_text": false,
      "is_archive": false,
      "is_media": false,
      "is_source": false,
      "is_script": false,
      "licenses": [],
      "license_expressions": [],
      "percentage_of_license_text": 0,
      "copyrights": [],
      "holders": [],
      "authors": [],
      "files_count": 2,
      "dirs_count": 0,
      "size_count": 13,
      "scan_errors": []
    },
    {
      "path": "importlib_resources/tests/data02/two/__init__.py",
      "type": "file",
      "name": "__init__.py",
      "base_name": "__init__",
      "extension": ".py",
      "size": 0,
      "date": "2020-11-24",
      "sha1": null,
      "md5": null,
      "sha256": null,
      "mime_type": "inode/x-empty",
      "file_type": "empty",
      "programming_language": "Python",
      "is_binary": false,
      "is_text": true,
      "is_archive": false,
      "is_media": false,
      "is_source": true,
      "is_script": false,
      "licenses": [],
      "license_expressions": [],
      "percentage_of_license_text": 0,
      "copyrights": [],
      "holders": [],
      "authors": [],
      "files_count": 0,
      "dirs_count": 0,
      "size_count": 0,
      "scan_errors": []
    },
    {
      "path": "importlib_resources/tests/data02/two/resource2.txt",
      "type": "file",
      "name": "resource2.txt",
      "base_name": "resource2",
      "extension": ".txt",
      "size": 13,
      "date": "2020-11-24",
      "sha1": "33cf09438773769e76c442b01eec11cbe93cf2ea",
      "md5": "91e7deb413bc54982761a4c1827a15b7",
      "sha256": "96dda36cddd3327f5088528cf37d97dfd6d4ffad94a6d0dd524a18ce4bc46e5d",
      "mime_type": "text/plain",
      "file_type": "ASCII text",
      "programming_language": null,
      "is_binary": false,
      "is_text": true,
      "is_archive": false,
      "is_media": false,
      "is_source": false,
      "is_script": false,
      "licenses": [],
      "license_expressions": [],
      "percentage_of_license_text": 0,
      "copyrights": [],
      "holders": [],
      "authors": [],
      "files_count": 0,
      "dirs_count": 0,
      "size_count": 0,
      "scan_errors": []
    },
    {
      "path": "importlib_resources/tests/namespacedata01",
      "type": "directory",
      "name": "namespacedata01",
      "base_name": "namespacedata01",
      "extension": "",
      "size": 0,
      "date": null,
      "sha1": null,
      "md5": null,
      "sha256": null,
      "mime_type": null,
      "file_type": null,
      "programming_language": null,
      "is_binary": false,
      "is_text": false,
      "is_archive": false,
      "is_media": false,
      "is_source": false,
      "is_script": false,
      "licenses": [],
      "license_expressions": [],
      "percentage_of_license_text": 0,
      "copyrights": [],
      "holders": [],
      "authors": [],
      "files_count": 3,
      "dirs_count": 0,
      "size_count": 68,
      "scan_errors": []
    },
    {
      "path": "importlib_resources/tests/namespacedata01/binary.file",
      "type": "file",
      "name": "binary.file",
      "base_name": "binary",
      "extension": ".file",
      "size": 4,
      "date": "2020-11-24",
      "sha1": "a02a05b025b928c039cf1ae7e8ee04e7c190c0db",
      "md5": "37b59afd592725f9305e484a5d7f5168",
      "sha256": "054edec1d0211f624fed0cbca9d4f9400b0e491c43742af2c5b0abebf0c990d8",
      "mime_type": "application/octet-stream",
      "file_type": "data",
      "programming_language": null,
      "is_binary": true,
      "is_text": false,
      "is_archive": false,
      "is_media": false,
      "is_source": false,
      "is_script": false,
      "licenses": [],
      "license_expressions": [],
      "percentage_of_license_text": 0,
      "copyrights": [],
      "holders": [],
      "authors": [],
      "files_count": 0,
      "dirs_count": 0,
      "size_count": 0,
      "scan_errors": []
    },
    {
      "path": "importlib_resources/tests/namespacedata01/utf-16.file",
      "type": "file",
      "name": "utf-16.file",
      "base_name": "utf-16",
      "extension": ".file",
      "size": 44,
      "date": "2020-11-24",
      "sha1": "3bf88b182117dce769d0cb03fb14ab771f827649",
      "md5": "ff6357f0940465f479305cbe0ba8f78f",
      "sha256": "b79abdaa1c57d2b62a22d04e33c0f7ca5c06f911eb9ce62d7932ed42beac17b8",
      "mime_type": "text/plain",
      "file_type": "Little-endian UTF-16 Unicode text",
      "programming_language": null,
      "is_binary": false,
      "is_text": true,
      "is_archive": false,
      "is_media": false,
      "is_source": false,
      "is_script": false,
      "licenses": [],
      "license_expressions": [],
      "percentage_of_license_text": 0,
      "copyrights": [],
      "holders": [],
      "authors": [],
      "files_count": 0,
      "dirs_count": 0,
      "size_count": 0,
      "scan_errors": []
    },
    {
      "path": "importlib_resources/tests/namespacedata01/utf-8.file",
      "type": "file",
      "name": "utf-8.file",
      "base_name": "utf-8",
      "extension": ".file",
      "size": 20,
      "date": "2020-11-24",
      "sha1": "7e13931923104bda5ae0fe40db20d0aaf51610f9",
      "md5": "58da4ec0dd953291e42b4a78598913da",
      "sha256": "9305a0606e3243e645d97fd603ae848d83e6c49467fb0f1a48e892f5ef2d2986",
      "mime_type": "text/plain",
      "file_type": "ASCII text",
      "programming_language": null,
      "is_binary": false,
      "is_text": true,
      "is_archive": false,
      "is_media": false,
      "is_source": false,
      "is_script": false,
      "licenses": [],
      "license_expressions": [],
      "percentage_of_license_text": 0,
      "copyrights": [],
      "holders": [],
      "authors": [],
      "files_count": 0,
      "dirs_count": 0,
      "size_count": 0,
      "scan_errors": []
    },
    {
      "path": "importlib_resources/tests/zipdata01",
      "type": "directory",
      "name": "zipdata01",
      "base_name": "zipdata01",
      "extension": "",
      "size": 0,
      "date": null,
      "sha1": null,
      "md5": null,
      "sha256": null,
      "mime_type": null,
      "file_type": null,
      "programming_language": null,
      "is_binary": false,
      "is_text": false,
      "is_archive": false,
      "is_media": false,
      "is_source": false,
      "is_script": false,
      "licenses": [],
      "license_expressions": [],
      "percentage_of_license_text": 0,
      "copyrights": [],
      "holders": [],
      "authors": [],
      "files_count": 2,
      "dirs_count": 0,
      "size_count": 1131,
      "scan_errors": []
    },
    {
      "path": "importlib_resources/tests/zipdata01/__init__.py",
      "type": "file",
      "name": "__init__.py",
      "base_name": "__init__",
      "extension": ".py",
      "size": 0,
      "date": "2020-11-24",
      "sha1": null,
      "md5": null,
      "sha256": null,
      "mime_type": "inode/x-empty",
      "file_type": "empty",
      "programming_language": "Python",
      "is_binary": false,
      "is_text": true,
      "is_archive": false,
      "is_media": false,
      "is_source": true,
      "is_script": false,
      "licenses": [],
      "license_expressions": [],
      "percentage_of_license_text": 0,
      "copyrights": [],
      "holders": [],
      "authors": [],
      "files_count": 0,
      "dirs_count": 0,
      "size_count": 0,
      "scan_errors": []
    },
    {
      "path": "importlib_resources/tests/zipdata01/ziptestdata.zip",
      "type": "file",
      "name": "ziptestdata.zip",
      "base_name": "ziptestdata",
      "extension": ".zip",
      "size": 1131,
      "date": "2020-11-24",
      "sha1": "0a2d881198b215a9792e88101e01a24ab2de8aaa",
      "md5": "892c22577865b7968056998dad4bc766",
      "sha256": "0187f9d5f8fcd0e282462b3ddefd839598ede6b33e55038fa6d48725b16d917c",
      "mime_type": "application/zip",
      "file_type": "Zip archive data, at least v2.0 to extract",
      "programming_language": null,
      "is_binary": true,
      "is_text": false,
      "is_archive": true,
      "is_media": false,
      "is_source": false,
      "is_script": false,
      "licenses": [],
      "license_expressions": [],
      "percentage_of_license_text": 0,
      "copyrights": [],
      "holders": [],
      "authors": [],
      "files_count": 0,
      "dirs_count": 0,
      "size_count": 0,
      "scan_errors": []
    },
    {
      "path": "importlib_resources/tests/zipdata02",
      "type": "directory",
      "name": "zipdata02",
      "base_name": "zipdata02",
      "extension": "",
      "size": 0,
      "date": null,
      "sha1": null,
      "md5": null,
      "sha256": null,
      "mime_type": null,
      "file_type": null,
      "programming_language": null,
      "is_binary": false,
      "is_text": false,
      "is_archive": false,
      "is_media": false,
      "is_source": false,
      "is_script": false,
      "licenses": [],
      "license_expressions": [],
      "percentage_of_license_text": 0,
      "copyrights": [],
      "holders": [],
      "authors": [],
      "files_count": 2,
      "dirs_count": 0,
      "size_count": 698,
      "scan_errors": []
    },
    {
      "path": "importlib_resources/tests/zipdata02/__init__.py",
      "type": "file",
      "name": "__init__.py",
      "base_name": "__init__",
      "extension": ".py",
      "size": 0,
      "date": "2020-11-24",
      "sha1": null,
      "md5": null,
      "sha256": null,
      "mime_type": "inode/x-empty",
      "file_type": "empty",
      "programming_language": "Python",
      "is_binary": false,
      "is_text": true,
      "is_archive": false,
      "is_media": false,
      "is_source": true,
      "is_script": false,
      "licenses": [],
      "license_expressions": [],
      "percentage_of_license_text": 0,
      "copyrights": [],
      "holders": [],
      "authors": [],
      "files_count": 0,
      "dirs_count": 0,
      "size_count": 0,
      "scan_errors": []
    },
    {
      "path": "importlib_resources/tests/zipdata02/ziptestdata.zip",
      "type": "file",
      "name": "ziptestdata.zip",
      "base_name": "ziptestdata",
      "extension": ".zip",
      "size": 698,
      "date": "2020-11-24",
      "sha1": "8af8581e9148f46d85e98a2a1cfeddba4f63b707",
      "md5": "47ac989e70cf52971983f732abe6d9cd",
      "sha256": "7ba1d7bd310e6d7bc970dc725f923cb6ee4cf3fea648df002da8477ea13b0030",
      "mime_type": "application/zip",
      "file_type": "Zip archive data, at least v2.0 to extract",
      "programming_language": null,
      "is_binary": true,
      "is_text": false,
      "is_archive": true,
      "is_media": false,
      "is_source": false,
      "is_script": false,
      "licenses": [],
      "license_expressions": [],
      "percentage_of_license_text": 0,
      "copyrights": [],
      "holders": [],
      "authors": [],
      "files_count": 0,
      "dirs_count": 0,
      "size_count": 0,
      "scan_errors": []
    }
  ]
}
